collective.timestamp-1.5-py3.12-nspkg.pth
collective/timestamp/__init__.py
collective/timestamp/adapters.py
collective/timestamp/adapters.zcml
collective/timestamp/configure.zcml
collective/timestamp/indexers.py
collective/timestamp/indexers.zcml
collective/timestamp/interfaces.py
collective/timestamp/permissions.zcml
collective/timestamp/profiles.zcml
collective/timestamp/setuphandlers.py
collective/timestamp/subscribers.py
collective/timestamp/subscribers.zcml
collective/timestamp/testing.py
collective/timestamp/upgrades.py
collective/timestamp/upgrades.zcml
collective/timestamp/utils.py
collective/timestamp/behaviors/__init__.py
collective/timestamp/behaviors/configure.zcml
collective/timestamp/behaviors/timestamp.py
collective/timestamp/browser/__init__.py
collective/timestamp/browser/action.py
collective/timestamp/browser/configure.zcml
collective/timestamp/browser/controlpanel.py
collective/timestamp/browser/infos.py
collective/timestamp/browser/rule.py
collective/timestamp/browser/viewlet.py
collective/timestamp/browser/templates/infos.pt
collective/timestamp/browser/templates/viewlet.pt
collective/timestamp/locales/README.rst
collective/timestamp/locales/__init__.py
collective/timestamp/locales/collective.timestamp.pot
collective/timestamp/locales/update.py
collective/timestamp/locales/update.sh
collective/timestamp/locales/en/LC_MESSAGES/collective.timestamp.po
collective/timestamp/locales/fr/LC_MESSAGES/collective.timestamp.po
collective/timestamp/profiles/default/actions.xml
collective/timestamp/profiles/default/browserlayer.xml
collective/timestamp/profiles/default/catalog.xml
collective/timestamp/profiles/default/controlpanel.xml
collective/timestamp/profiles/default/metadata.xml
collective/timestamp/profiles/default/registry.xml
collective/timestamp/profiles/default/rolemap.xml
collective/timestamp/profiles/testing/contentrules.xml
collective/timestamp/profiles/testing/metadata.xml
collective/timestamp/profiles/testing/registry.xml
collective_timestamp-1.5.dist-info/licenses/LICENSE.GPL
collective_timestamp-1.5.dist-info/licenses/LICENSE.rst
collective_timestamp-1.5.dist-info/METADATA
collective_timestamp-1.5.dist-info/WHEEL
collective_timestamp-1.5.dist-info/entry_points.txt
collective_timestamp-1.5.dist-info/namespace_packages.txt
collective_timestamp-1.5.dist-info/top_level.txt
collective_timestamp-1.5.dist-info/RECORD
